{
  "hash": "0c4d54f0",
  "configHash": "ae72ce40",
  "lockfileHash": "a5824cd4",
  "browserHash": "090d0fbd",
  "optimized": {
    "vue": {
      "src": "../../../../node_modules/vue/dist/vue.runtime.esm-bundler.js",
      "file": "vue.js",
      "fileHash": "0d19fa86",
      "needsInterop": false
    },
    "vitepress > @vue/devtools-api": {
      "src": "../../../../node_modules/@vue/devtools-api/dist/index.js",
      "file": "vitepress___@vue_devtools-api.js",
      "fileHash": "e4074814",
      "needsInterop": false
    },
    "vitepress > @vueuse/core": {
      "src": "../../../../node_modules/@vueuse/core/index.mjs",
      "file": "vitepress___@vueuse_core.js",
      "fileHash": "1b29d64f",
      "needsInterop": false
    }
  },
  "chunks": {
    "chunk-URVHZSMY": {
      "file": "chunk-URVHZSMY.js"
    }
  }
}